amply/__init__.py
amply/amply.py
amply-0.1.6.dist-info/AUTHORS
amply-0.1.6.dist-info/LICENSE
amply-0.1.6.dist-info/METADATA
amply-0.1.6.dist-info/WHEEL
amply-0.1.6.dist-info/top_level.txt
amply-0.1.6.dist-info/RECORD
