Metadata-Version: 2.1
Name: amply
Version: 0.1.6
Summary: Amply allows you to load and manipulate AMPL/GLPK data as Python data structures
Home-page: http://github.com/willu47/amply
Author: Will Usher,Christophe-Marie Duquesne,Stuart Mitchell,Franco Peschiera,Stu,smit023,Q. Lim
Author-email: wusher@kth.se
License: Eclipse Public License 1.0 (EPL-1.0)
Project-URL: Bug Tracker, http://github.com/willu47/amply/issues
Project-URL: Documentation, http://github.com/willu47/amply/README.rst
Project-URL: Source Code, http://github.com/willu47/amply
Keywords: ampl gmpl
Classifier: License :: OSI Approved :: Eclipse Public License 1.0 (EPL-1.0)
Requires-Python: >=2.7, !=3.0.*, !=3.1.*, !=3.2.*, !=3.3.*
License-File: LICENSE
License-File: AUTHORS
